<?xml version="1.0" encoding="UTF-8"?>
<xml>
  <EquipAssignment>
    <Facility>PNT1</Facility>
    <Equipment>1</Equipment>
    <LBound>326</LBound>
    <UBound>344</UBound>
  </EquipAssignment>
  <EquipAssignment>
    <Facility>PNT1</Facility>
    <Equipment>1</Equipment>
    <LBound>364</LBound>
    <UBound>381</UBound>
  </EquipAssignment>
  <EquipAssignment>
    <Facility>PNT1</Facility>
    <Equipment>1</Equipment>
    <LBound>400</LBound>
    <UBound>405</UBound>
  </EquipAssignment>
  <EquipAssignment>
    <Facility>PNT1</Facility>
    <Equipment>1</Equipment>
    <LBound>412</LBound>
    <UBound>419</UBound>
  </EquipAssignment>
  <EquipAssignment>
    <Facility>PNT1</Facility>
    <Equipment>1</Equipment>
    <LBound>428</LBound>
    <UBound>433</UBound>
  </EquipAssignment>
  <EquipAssignment>
    <Facility>PNT1</Facility>
    <Equipment>1</Equipment>
    <LBound>440</LBound>
    <UBound>445</UBound>
  </EquipAssignment>
  <EquipAssignment>
    <Facility>PNT1</Facility>
    <Equipment>1</Equipment>
    <LBound>452</LBound>
    <UBound>456</UBound>
  </EquipAssignment>
  <EquipAssignment>
    <Facility>PNT1</Facility>
    <Equipment>1</Equipment>
    <LBound>462</LBound>
    <UBound>470</UBound>
  </EquipAssignment>
  <EquipAssignment>
    <Facility>PNT1</Facility>
    <Equipment>1</Equipment>
    <LBound>480</LBound>
    <UBound>510</UBound>
  </EquipAssignment>
  <EquipAssignment>
    <Facility>PNT1</Facility>
    <Equipment>1</Equipment>
    <LBound>542</LBound>
    <UBound>547</UBound>
  </EquipAssignment>
  <EquipAssignment>
    <Facility>PNT1</Facility>
    <Equipment>1</Equipment>
    <LBound>554</LBound>
    <UBound>582</UBound>
  </EquipAssignment>
  <EquipAssignment>
    <Facility>PNT1</Facility>
    <Equipment>1</Equipment>
    <LBound>612</LBound>
    <UBound>641</UBound>
  </EquipAssignment>
  <EquipAssignment>
    <Facility>PNT1</Facility>
    <Equipment>1</Equipment>
    <LBound>673</LBound>
    <UBound>685</UBound>
  </EquipAssignment>
  <EquipAssignment>
    <Facility>PNT1</Facility>
    <Equipment>1</Equipment>
    <LBound>699</LBound>
    <UBound>715</UBound>
  </EquipAssignment>
  <EquipAssignment>
    <Facility>PNT1</Facility>
    <Equipment>1</Equipment>
    <LBound>733</LBound>
    <UBound>777</UBound>
  </EquipAssignment>
  <EquipAssignment>
    <Facility>PNT1</Facility>
    <Equipment>1</Equipment>
    <LBound>823</LBound>
    <UBound>832</UBound>
  </EquipAssignment>
  <EquipAssignment>
    <Facility>PNT1</Facility>
    <Equipment>1</Equipment>
    <LBound>843</LBound>
    <UBound>858</UBound>
  </EquipAssignment>
  <EquipAssignment>
    <Facility>PNT1</Facility>
    <Equipment>1</Equipment>
    <LBound>875</LBound>
    <UBound>881</UBound>
  </EquipAssignment>
  <EquipAssignment>
    <Facility>PNT1</Facility>
    <Equipment>1</Equipment>
    <LBound>889</LBound>
    <UBound>900</UBound>
  </EquipAssignment>
  <EquipAssignment>
    <Facility>PNT1</Facility>
    <Equipment>1</Equipment>
    <LBound>913</LBound>
    <UBound>916</UBound>
  </EquipAssignment>
  <EquipAssignment>
    <Facility>PNT1</Facility>
    <Equipment>1</Equipment>
    <LBound>921</LBound>
    <UBound>925</UBound>
  </EquipAssignment>
  <EquipAssignment>
    <Facility>PNT1</Facility>
    <Equipment>1</Equipment>
    <LBound>931</LBound>
    <UBound>936</UBound>
  </EquipAssignment>
  <EquipAssignment>
    <Facility>PNT1</Facility>
    <Equipment>1</Equipment>
    <LBound>943</LBound>
    <UBound>945</UBound>
  </EquipAssignment>
  <EquipAssignment>
    <Facility>PNT1</Facility>
    <Equipment>1</Equipment>
    <LBound>949</LBound>
    <UBound>964</UBound>
  </EquipAssignment>
  <EquipAssignment>
    <Facility>PNT1</Facility>
    <Equipment>1</Equipment>
    <LBound>981</LBound>
    <UBound>988</UBound>
  </EquipAssignment>
  <EquipAssignment>
    <Facility>PNT2</Facility>
    <Equipment>1</Equipment>
    <LBound>803</LBound>
    <UBound>822</UBound>
  </EquipAssignment>
  <EquipAssignment>
    <Facility>PNT1</Facility>
    <Equipment>2</Equipment>
    <LBound>345</LBound>
    <UBound>363</UBound>
  </EquipAssignment>
  <EquipAssignment>
    <Facility>PNT1</Facility>
    <Equipment>2</Equipment>
    <LBound>382</LBound>
    <UBound>399</UBound>
  </EquipAssignment>
  <EquipAssignment>
    <Facility>PNT1</Facility>
    <Equipment>2</Equipment>
    <LBound>406</LBound>
    <UBound>411</UBound>
  </EquipAssignment>
  <EquipAssignment>
    <Facility>PNT1</Facility>
    <Equipment>2</Equipment>
    <LBound>420</LBound>
    <UBound>427</UBound>
  </EquipAssignment>
  <EquipAssignment>
    <Facility>PNT1</Facility>
    <Equipment>2</Equipment>
    <LBound>434</LBound>
    <UBound>439</UBound>
  </EquipAssignment>
  <EquipAssignment>
    <Facility>PNT1</Facility>
    <Equipment>2</Equipment>
    <LBound>446</LBound>
    <UBound>451</UBound>
  </EquipAssignment>
  <EquipAssignment>
    <Facility>PNT1</Facility>
    <Equipment>2</Equipment>
    <LBound>457</LBound>
    <UBound>461</UBound>
  </EquipAssignment>
  <EquipAssignment>
    <Facility>PNT1</Facility>
    <Equipment>2</Equipment>
    <LBound>471</LBound>
    <UBound>479</UBound>
  </EquipAssignment>
  <EquipAssignment>
    <Facility>PNT1</Facility>
    <Equipment>2</Equipment>
    <LBound>511</LBound>
    <UBound>541</UBound>
  </EquipAssignment>
  <EquipAssignment>
    <Facility>PNT1</Facility>
    <Equipment>2</Equipment>
    <LBound>548</LBound>
    <UBound>553</UBound>
  </EquipAssignment>
  <EquipAssignment>
    <Facility>PNT1</Facility>
    <Equipment>2</Equipment>
    <LBound>583</LBound>
    <UBound>611</UBound>
  </EquipAssignment>
  <EquipAssignment>
    <Facility>PNT1</Facility>
    <Equipment>2</Equipment>
    <LBound>643</LBound>
    <UBound>672</UBound>
  </EquipAssignment>
  <EquipAssignment>
    <Facility>PNT1</Facility>
    <Equipment>2</Equipment>
    <LBound>686</LBound>
    <UBound>698</UBound>
  </EquipAssignment>
  <EquipAssignment>
    <Facility>PNT1</Facility>
    <Equipment>2</Equipment>
    <LBound>716</LBound>
    <UBound>732</UBound>
  </EquipAssignment>
  <EquipAssignment>
    <Facility>PNT1</Facility>
    <Equipment>2</Equipment>
    <LBound>778</LBound>
    <UBound>822</UBound>
  </EquipAssignment>
  <EquipAssignment>
    <Facility>PNT1</Facility>
    <Equipment>2</Equipment>
    <LBound>833</LBound>
    <UBound>842</UBound>
  </EquipAssignment>
  <EquipAssignment>
    <Facility>PNT1</Facility>
    <Equipment>2</Equipment>
    <LBound>859</LBound>
    <UBound>874</UBound>
  </EquipAssignment>
  <EquipAssignment>
    <Facility>PNT1</Facility>
    <Equipment>2</Equipment>
    <LBound>882</LBound>
    <UBound>888</UBound>
  </EquipAssignment>
  <EquipAssignment>
    <Facility>PNT1</Facility>
    <Equipment>2</Equipment>
    <LBound>901</LBound>
    <UBound>912</UBound>
  </EquipAssignment>
  <EquipAssignment>
    <Facility>PNT1</Facility>
    <Equipment>2</Equipment>
    <LBound>917</LBound>
    <UBound>920</UBound>
  </EquipAssignment>
  <EquipAssignment>
    <Facility>PNT1</Facility>
    <Equipment>2</Equipment>
    <LBound>926</LBound>
    <UBound>930</UBound>
  </EquipAssignment>
  <EquipAssignment>
    <Facility>PNT1</Facility>
    <Equipment>2</Equipment>
    <LBound>937</LBound>
    <UBound>942</UBound>
  </EquipAssignment>
  <EquipAssignment>
    <Facility>PNT1</Facility>
    <Equipment>2</Equipment>
    <LBound>946</LBound>
    <UBound>948</UBound>
  </EquipAssignment>
  <EquipAssignment>
    <Facility>PNT1</Facility>
    <Equipment>2</Equipment>
    <LBound>965</LBound>
    <UBound>980</UBound>
  </EquipAssignment>
  <EquipAssignment>
    <Facility>PNT1</Facility>
    <Equipment>2</Equipment>
    <LBound>989</LBound>
    <UBound>996</UBound>
  </EquipAssignment>
  <EquipAssignment>
    <Facility>PNT2</Facility>
    <Equipment>2</Equipment>
    <LBound>823</LBound>
    <UBound>842</UBound>
  </EquipAssignment>
  <EquipAssignment>
    <Facility>PNT2</Facility>
    <Equipment>3</Equipment>
    <LBound>1</LBound>
    <UBound>19</UBound>
  </EquipAssignment>
  <EquipAssignment>
    <Facility>PNT2</Facility>
    <Equipment>3</Equipment>
    <LBound>77</LBound>
    <UBound>94</UBound>
  </EquipAssignment>
  <EquipAssignment>
    <Facility>PNT2</Facility>
    <Equipment>3</Equipment>
    <LBound>149</LBound>
    <UBound>154</UBound>
  </EquipAssignment>
  <EquipAssignment>
    <Facility>PNT2</Facility>
    <Equipment>3</Equipment>
    <LBound>161</LBound>
    <UBound>168</UBound>
  </EquipAssignment>
  <EquipAssignment>
    <Facility>PNT2</Facility>
    <Equipment>3</Equipment>
    <LBound>193</LBound>
    <UBound>198</UBound>
  </EquipAssignment>
  <EquipAssignment>
    <Facility>PNT2</Facility>
    <Equipment>3</Equipment>
    <LBound>205</LBound>
    <UBound>210</UBound>
  </EquipAssignment>
  <EquipAssignment>
    <Facility>PNT2</Facility>
    <Equipment>3</Equipment>
    <LBound>229</LBound>
    <UBound>233</UBound>
  </EquipAssignment>
  <EquipAssignment>
    <Facility>PNT2</Facility>
    <Equipment>3</Equipment>
    <LBound>249</LBound>
    <UBound>257</UBound>
  </EquipAssignment>
  <EquipAssignment>
    <Facility>PNT2</Facility>
    <Equipment>3</Equipment>
    <LBound>267</LBound>
    <UBound>297</UBound>
  </EquipAssignment>
  <EquipAssignment>
    <Facility>PNT2</Facility>
    <Equipment>3</Equipment>
    <LBound>329</LBound>
    <UBound>334</UBound>
  </EquipAssignment>
  <EquipAssignment>
    <Facility>PNT2</Facility>
    <Equipment>3</Equipment>
    <LBound>341</LBound>
    <UBound>369</UBound>
  </EquipAssignment>
  <EquipAssignment>
    <Facility>PNT2</Facility>
    <Equipment>3</Equipment>
    <LBound>399</LBound>
    <UBound>428</UBound>
  </EquipAssignment>
  <EquipAssignment>
    <Facility>PNT2</Facility>
    <Equipment>3</Equipment>
    <LBound>459</LBound>
    <UBound>471</UBound>
  </EquipAssignment>
  <EquipAssignment>
    <Facility>PNT2</Facility>
    <Equipment>3</Equipment>
    <LBound>485</LBound>
    <UBound>501</UBound>
  </EquipAssignment>
  <EquipAssignment>
    <Facility>PNT2</Facility>
    <Equipment>3</Equipment>
    <LBound>519</LBound>
    <UBound>563</UBound>
  </EquipAssignment>
  <EquipAssignment>
    <Facility>PNT2</Facility>
    <Equipment>3</Equipment>
    <LBound>609</LBound>
    <UBound>618</UBound>
  </EquipAssignment>
  <EquipAssignment>
    <Facility>PNT2</Facility>
    <Equipment>3</Equipment>
    <LBound>629</LBound>
    <UBound>644</UBound>
  </EquipAssignment>
  <EquipAssignment>
    <Facility>PNT2</Facility>
    <Equipment>3</Equipment>
    <LBound>661</LBound>
    <UBound>667</UBound>
  </EquipAssignment>
  <EquipAssignment>
    <Facility>PNT2</Facility>
    <Equipment>3</Equipment>
    <LBound>675</LBound>
    <UBound>686</UBound>
  </EquipAssignment>
  <EquipAssignment>
    <Facility>PNT2</Facility>
    <Equipment>3</Equipment>
    <LBound>699</LBound>
    <UBound>702</UBound>
  </EquipAssignment>
  <EquipAssignment>
    <Facility>PNT2</Facility>
    <Equipment>3</Equipment>
    <LBound>715</LBound>
    <UBound>719</UBound>
  </EquipAssignment>
  <EquipAssignment>
    <Facility>PNT2</Facility>
    <Equipment>3</Equipment>
    <LBound>735</LBound>
    <UBound>740</UBound>
  </EquipAssignment>
  <EquipAssignment>
    <Facility>PNT2</Facility>
    <Equipment>3</Equipment>
    <LBound>771</LBound>
    <UBound>786</UBound>
  </EquipAssignment>
  <EquipAssignment>
    <Facility>PNT2</Facility>
    <Equipment>4</Equipment>
    <LBound>20</LBound>
    <UBound>38</UBound>
  </EquipAssignment>
  <EquipAssignment>
    <Facility>PNT2</Facility>
    <Equipment>4</Equipment>
    <LBound>95</LBound>
    <UBound>112</UBound>
  </EquipAssignment>
  <EquipAssignment>
    <Facility>PNT2</Facility>
    <Equipment>4</Equipment>
    <LBound>155</LBound>
    <UBound>160</UBound>
  </EquipAssignment>
  <EquipAssignment>
    <Facility>PNT2</Facility>
    <Equipment>4</Equipment>
    <LBound>169</LBound>
    <UBound>176</UBound>
  </EquipAssignment>
  <EquipAssignment>
    <Facility>PNT2</Facility>
    <Equipment>4</Equipment>
    <LBound>199</LBound>
    <UBound>204</UBound>
  </EquipAssignment>
  <EquipAssignment>
    <Facility>PNT2</Facility>
    <Equipment>4</Equipment>
    <LBound>211</LBound>
    <UBound>216</UBound>
  </EquipAssignment>
  <EquipAssignment>
    <Facility>PNT2</Facility>
    <Equipment>4</Equipment>
    <LBound>234</LBound>
    <UBound>238</UBound>
  </EquipAssignment>
  <EquipAssignment>
    <Facility>PNT2</Facility>
    <Equipment>4</Equipment>
    <LBound>258</LBound>
    <UBound>266</UBound>
  </EquipAssignment>
  <EquipAssignment>
    <Facility>PNT2</Facility>
    <Equipment>4</Equipment>
    <LBound>298</LBound>
    <UBound>328</UBound>
  </EquipAssignment>
  <EquipAssignment>
    <Facility>PNT2</Facility>
    <Equipment>4</Equipment>
    <LBound>335</LBound>
    <UBound>340</UBound>
  </EquipAssignment>
  <EquipAssignment>
    <Facility>PNT2</Facility>
    <Equipment>4</Equipment>
    <LBound>370</LBound>
    <UBound>398</UBound>
  </EquipAssignment>
  <EquipAssignment>
    <Facility>PNT2</Facility>
    <Equipment>4</Equipment>
    <LBound>429</LBound>
    <UBound>458</UBound>
  </EquipAssignment>
  <EquipAssignment>
    <Facility>PNT2</Facility>
    <Equipment>4</Equipment>
    <LBound>472</LBound>
    <UBound>484</UBound>
  </EquipAssignment>
  <EquipAssignment>
    <Facility>PNT2</Facility>
    <Equipment>4</Equipment>
    <LBound>502</LBound>
    <UBound>518</UBound>
  </EquipAssignment>
  <EquipAssignment>
    <Facility>PNT2</Facility>
    <Equipment>4</Equipment>
    <LBound>564</LBound>
    <UBound>608</UBound>
  </EquipAssignment>
  <EquipAssignment>
    <Facility>PNT2</Facility>
    <Equipment>4</Equipment>
    <LBound>619</LBound>
    <UBound>628</UBound>
  </EquipAssignment>
  <EquipAssignment>
    <Facility>PNT2</Facility>
    <Equipment>4</Equipment>
    <LBound>645</LBound>
    <UBound>660</UBound>
  </EquipAssignment>
  <EquipAssignment>
    <Facility>PNT2</Facility>
    <Equipment>4</Equipment>
    <LBound>668</LBound>
    <UBound>674</UBound>
  </EquipAssignment>
  <EquipAssignment>
    <Facility>PNT2</Facility>
    <Equipment>4</Equipment>
    <LBound>687</LBound>
    <UBound>698</UBound>
  </EquipAssignment>
  <EquipAssignment>
    <Facility>PNT2</Facility>
    <Equipment>4</Equipment>
    <LBound>703</LBound>
    <UBound>706</UBound>
  </EquipAssignment>
  <EquipAssignment>
    <Facility>PNT2</Facility>
    <Equipment>4</Equipment>
    <LBound>720</LBound>
    <UBound>724</UBound>
  </EquipAssignment>
  <EquipAssignment>
    <Facility>PNT2</Facility>
    <Equipment>4</Equipment>
    <LBound>741</LBound>
    <UBound>746</UBound>
  </EquipAssignment>
  <EquipAssignment>
    <Facility>PNT2</Facility>
    <Equipment>4</Equipment>
    <LBound>787</LBound>
    <UBound>802</UBound>
  </EquipAssignment>
  <EquipAssignment>
    <Facility>PNT2</Facility>
    <Equipment>5</Equipment>
    <LBound>39</LBound>
    <UBound>57</UBound>
  </EquipAssignment>
  <EquipAssignment>
    <Facility>PNT2</Facility>
    <Equipment>5</Equipment>
    <LBound>113</LBound>
    <UBound>130</UBound>
  </EquipAssignment>
  <EquipAssignment>
    <Facility>PNT2</Facility>
    <Equipment>5</Equipment>
    <LBound>177</LBound>
    <UBound>184</UBound>
  </EquipAssignment>
  <EquipAssignment>
    <Facility>PNT2</Facility>
    <Equipment>5</Equipment>
    <LBound>217</LBound>
    <UBound>222</UBound>
  </EquipAssignment>
  <EquipAssignment>
    <Facility>PNT2</Facility>
    <Equipment>5</Equipment>
    <LBound>239</LBound>
    <UBound>243</UBound>
  </EquipAssignment>
  <EquipAssignment>
    <Facility>PNT2</Facility>
    <Equipment>5</Equipment>
    <LBound>707</LBound>
    <UBound>710</UBound>
  </EquipAssignment>
  <EquipAssignment>
    <Facility>PNT2</Facility>
    <Equipment>5</Equipment>
    <LBound>725</LBound>
    <UBound>729</UBound>
  </EquipAssignment>
  <EquipAssignment>
    <Facility>PNT2</Facility>
    <Equipment>5</Equipment>
    <LBound>747</LBound>
    <UBound>752</UBound>
  </EquipAssignment>
  <EquipAssignment>
    <Facility>PNT2</Facility>
    <Equipment>6</Equipment>
    <LBound>58</LBound>
    <UBound>76</UBound>
  </EquipAssignment>
  <EquipAssignment>
    <Facility>PNT2</Facility>
    <Equipment>6</Equipment>
    <LBound>131</LBound>
    <UBound>148</UBound>
  </EquipAssignment>
  <EquipAssignment>
    <Facility>PNT2</Facility>
    <Equipment>6</Equipment>
    <LBound>185</LBound>
    <UBound>192</UBound>
  </EquipAssignment>
  <EquipAssignment>
    <Facility>PNT2</Facility>
    <Equipment>6</Equipment>
    <LBound>223</LBound>
    <UBound>228</UBound>
  </EquipAssignment>
  <EquipAssignment>
    <Facility>PNT2</Facility>
    <Equipment>6</Equipment>
    <LBound>244</LBound>
    <UBound>248</UBound>
  </EquipAssignment>
  <EquipAssignment>
    <Facility>PNT2</Facility>
    <Equipment>6</Equipment>
    <LBound>711</LBound>
    <UBound>714</UBound>
  </EquipAssignment>
  <EquipAssignment>
    <Facility>PNT2</Facility>
    <Equipment>6</Equipment>
    <LBound>730</LBound>
    <UBound>734</UBound>
  </EquipAssignment>
  <EquipAssignment>
    <Facility>PNT2</Facility>
    <Equipment>6</Equipment>
    <LBound>753</LBound>
    <UBound>758</UBound>
  </EquipAssignment>
  <AssocData>
    <Equipment>1</Equipment>
    <StyleProg></StyleProg>
    <StyleVar></StyleVar>
    <ColorProg></ColorProg>
    <ColorVar></ColorVar>
    <ValveProg>PASHELL</ValveProg>
    <ValveVar>tShellCmos[1].cur_sysc_idx</ValveVar>
    <JobProg>PASHELL</JobProg>
    <JobVar>tShellDram[1].job_name</JobVar>
    <ProcessProg>PASHELL</ProcessProg>
    <ProcessVar>tShellCmos[1].path_name</ProcessVar>
    <NodeProg></NodeProg>
    <NodeVar></NodeVar>
  </AssocData>
  <AssocData>
    <Equipment>2</Equipment>
    <StyleProg></StyleProg>
    <StyleVar></StyleVar>
    <ColorProg></ColorProg>
    <ColorVar></ColorVar>
    <ValveProg>PASHELL</ValveProg>
    <ValveVar>tShellCmos[2].cur_sysc_idx</ValveVar>
    <JobProg>PASHELL</JobProg>
    <JobVar>tShellDram[2].job_name</JobVar>
    <ProcessProg>PASHELL</ProcessProg>
    <ProcessVar>tShellCmos[2].path_name</ProcessVar>
    <NodeProg></NodeProg>
    <NodeVar></NodeVar>
  </AssocData>
  <AssocData>
    <Equipment>3</Equipment>
    <StyleProg></StyleProg>
    <StyleVar></StyleVar>
    <ColorProg></ColorProg>
    <ColorVar></ColorVar>
    <ValveProg>PASHELL</ValveProg>
    <ValveVar></ValveVar>
    <JobProg>PASHELL</JobProg>
    <JobVar>tShellDram[3].job_name</JobVar>
    <ProcessProg>PASHELL</ProcessProg>
    <ProcessVar>tShellCmos[3].path_name</ProcessVar>
    <NodeProg></NodeProg>
    <NodeVar></NodeVar>
  </AssocData>
  <AssocData>
    <Equipment>4</Equipment>
    <StyleProg></StyleProg>
    <StyleVar></StyleVar>
    <ColorProg></ColorProg>
    <ColorVar></ColorVar>
    <ValveProg>PASHELL</ValveProg>
    <ValveVar></ValveVar>
    <JobProg>PASHELL</JobProg>
    <JobVar>tShellDram[4].job_name</JobVar>
    <ProcessProg>PASHELL</ProcessProg>
    <ProcessVar>tShellCmos[4].path_name</ProcessVar>
    <NodeProg></NodeProg>
    <NodeVar></NodeVar>
  </AssocData>
  <AssocData>
    <Equipment>5</Equipment>
    <StyleProg></StyleProg>
    <StyleVar></StyleVar>
    <ColorProg></ColorProg>
    <ColorVar></ColorVar>
    <ValveProg>PASHELL</ValveProg>
    <ValveVar></ValveVar>
    <JobProg>PASHELL</JobProg>
    <JobVar>tShellDram[5].job_name</JobVar>
    <ProcessProg>PASHELL</ProcessProg>
    <ProcessVar>tShellCmos[5].path_name</ProcessVar>
    <NodeProg></NodeProg>
    <NodeVar></NodeVar>
  </AssocData>
  <AssocData>
    <Equipment>6</Equipment>
    <StyleProg></StyleProg>
    <StyleVar></StyleVar>
    <ColorProg></ColorProg>
    <ColorVar></ColorVar>
    <ValveProg>PASHELL</ValveProg>
    <ValveVar></ValveVar>
    <JobProg>PASHELL</JobProg>
    <JobVar>tShellDram[6].job_name</JobVar>
    <ProcessProg>PASHELL</ProcessProg>
    <ProcessVar>tShellCmos[6].path_name</ProcessVar>
    <NodeProg></NodeProg>
    <NodeVar></NodeVar>
  </AssocData>
</xml>